mako/__init__.py
mako/_ast_util.py
mako/ast.py
mako/cache.py
mako/cmd.py
mako/codegen.py
mako/compat.py
mako/exceptions.py
mako/filters.py
mako/lexer.py
mako/lookup.py
mako/parsetree.py
mako/pygen.py
mako/pyparser.py
mako/runtime.py
mako/template.py
mako/util.py
mako/ext/__init__.py
mako/ext/autohandler.py
mako/ext/babelplugin.py
mako/ext/beaker_cache.py
mako/ext/extract.py
mako/ext/linguaplugin.py
mako/ext/preprocessors.py
mako/ext/pygmentplugin.py
mako/ext/turbogears.py
mako/testing/__init__.py
mako/testing/_config.py
mako/testing/assertions.py
mako/testing/config.py
mako/testing/exclusions.py
mako/testing/fixtures.py
mako/testing/helpers.py
Mako-1.3.4.dist-info/LICENSE
Mako-1.3.4.dist-info/METADATA
Mako-1.3.4.dist-info/WHEEL
Mako-1.3.4.dist-info/entry_points.txt
Mako-1.3.4.dist-info/top_level.txt
Mako-1.3.4.dist-info/RECORD
