Metadata-Version: 2.1
Name: Mako
Version: 1.3.4
Summary: A super-fast templating language that borrows the best ideas from the existing templating languages.
Home-page: https://www.makotemplates.org/
Author: Mike Bayer
Author-email: mike@zzzcomputing.com
License: MIT
Project-URL: Documentation, https://docs.makotemplates.org
Project-URL: Issue Tracker, https://github.com/sqlalchemy/mako
Classifier: Development Status :: 5 - Production/Stable
Classifier: License :: OSI Approved :: MIT License
Classifier: Environment :: Web Environment
Classifier: Intended Audience :: Developers
Classifier: Programming Language :: Python
Classifier: Programming Language :: Python :: 3
Classifier: Programming Language :: Python :: 3.8
Classifier: Programming Language :: Python :: 3.9
Classifier: Programming Language :: Python :: 3.10
Classifier: Programming Language :: Python :: 3.11
Classifier: Programming Language :: Python :: 3.12
Classifier: Programming Language :: Python :: Implementation :: CPython
Classifier: Programming Language :: Python :: Implementation :: PyPy
Classifier: Topic :: Internet :: WWW/HTTP :: Dynamic Content
Requires-Python: >=3.8
License-File: LICENSE
Requires-Dist: MarkupSafe>=0.9.2
Provides-Extra: testing
Requires-Dist: pytest; extra == "testing"
Provides-Extra: babel
Requires-Dist: Babel; extra == "babel"
Provides-Extra: lingua
Requires-Dist: lingua; extra == "lingua"
